psf/__init__.py
psf/license.md
psf/openal32.dll
psf/pysfml261.cp311-win_amd64.pyd
psf/pysfml261.pyx
psf/pysfml261_constants.cp311-win_amd64.pyd
psf/sf_constants.pyx
psf/sfml-audio-2.dll
psf/sfml-graphics-2.dll
psf/sfml-system-2.dll
psf/sfml-window-2.dll
tortoise_sfml-0.1.0.dist-info/METADATA
tortoise_sfml-0.1.0.dist-info/WHEEL
tortoise_sfml-0.1.0.dist-info/top_level.txt
tortoise_sfml-0.1.0.dist-info/RECORD
