Metadata-Version: 2.4
Name: tortoise-sfml
Version: 0.1.0
Summary: SFML 2.6.1 cython binding for python
Author: CoffeeTortoise
Author-email: e.8ychkov@yandex.ru
License: zlib
Dynamic: author
Dynamic: author-email
Dynamic: license
Dynamic: summary
